rembg/__init__.py
rembg/_version.py
rembg/bg.py
rembg/cli.py
rembg/session_factory.py
rembg/commands/__init__.py
rembg/commands/b_command.py
rembg/commands/d_command.py
rembg/commands/i_command.py
rembg/commands/p_command.py
rembg/commands/s_command.py
rembg/sessions/__init__.py
rembg/sessions/base.py
rembg/sessions/birefnet_cod.py
rembg/sessions/birefnet_dis.py
rembg/sessions/birefnet_general.py
rembg/sessions/birefnet_general_lite.py
rembg/sessions/birefnet_hrsod.py
rembg/sessions/birefnet_massive.py
rembg/sessions/birefnet_portrait.py
rembg/sessions/dis_anime.py
rembg/sessions/dis_general_use.py
rembg/sessions/sam.py
rembg/sessions/silueta.py
rembg/sessions/u2net.py
rembg/sessions/u2net_cloth_seg.py
rembg/sessions/u2net_custom.py
rembg/sessions/u2net_human_seg.py
rembg/sessions/u2netp.py
rembg-2.0.60.dist-info/LICENSE.txt
rembg-2.0.60.dist-info/METADATA
rembg-2.0.60.dist-info/WHEEL
rembg-2.0.60.dist-info/entry_points.txt
rembg-2.0.60.dist-info/top_level.txt
rembg-2.0.60.dist-info/RECORD
