Metadata-Version: 2.1
Name: rembg
Version: 2.0.60
Summary: Remove image background
Home-page: https://github.com/danielgatis/rembg
Author: Daniel Gatis
Author-email: danielgatis@gmail.com
Keywords: remove,background,u2net
Classifier: License :: OSI Approved :: MIT License
Classifier: Topic :: Scientific/Engineering
Classifier: Topic :: Scientific/Engineering :: Mathematics
Classifier: Topic :: Scientific/Engineering :: Artificial Intelligence
Classifier: Topic :: Software Development
Classifier: Topic :: Software Development :: Libraries
Classifier: Topic :: Software Development :: Libraries :: Python Modules
Classifier: Programming Language :: Python
Classifier: Programming Language :: Python :: 3 :: Only
Classifier: Programming Language :: Python :: 3.8
Classifier: Programming Language :: Python :: 3.9
Classifier: Programming Language :: Python :: 3.10
Classifier: Programming Language :: Python :: 3.11
Classifier: Programming Language :: Python :: 3.12
Requires-Python: >=3.8, <3.13
License-File: LICENSE.txt
Requires-Dist: jsonschema
Requires-Dist: numpy
Requires-Dist: opencv-python-headless
Requires-Dist: pillow
Requires-Dist: pooch
Requires-Dist: pymatting
Requires-Dist: scikit-image
Requires-Dist: scipy
Requires-Dist: tqdm
Provides-Extra: dev
Requires-Dist: bandit; extra == "dev"
Requires-Dist: black; extra == "dev"
Requires-Dist: flake8; extra == "dev"
Requires-Dist: imagehash; extra == "dev"
Requires-Dist: isort; extra == "dev"
Requires-Dist: mypy; extra == "dev"
Requires-Dist: pytest; extra == "dev"
Requires-Dist: setuptools; extra == "dev"
Requires-Dist: twine; extra == "dev"
Requires-Dist: wheel; extra == "dev"
Provides-Extra: cpu
Requires-Dist: onnxruntime; extra == "cpu"
Provides-Extra: gpu
Requires-Dist: onnxruntime-gpu; extra == "gpu"
Provides-Extra: cli
Requires-Dist: aiohttp; extra == "cli"
Requires-Dist: asyncer; extra == "cli"
Requires-Dist: click; extra == "cli"
Requires-Dist: fastapi; extra == "cli"
Requires-Dist: filetype; extra == "cli"
Requires-Dist: gradio; extra == "cli"
Requires-Dist: python-multipart; extra == "cli"
Requires-Dist: uvicorn; extra == "cli"
Requires-Dist: watchdog; extra == "cli"
